naff_audio/__init__.py
naff_audio/audio_queue.py
naff_audio/yt_audio.py
naff_audio-1.2.0.dist-info/LICENSE.md
naff_audio-1.2.0.dist-info/METADATA
naff_audio-1.2.0.dist-info/WHEEL
naff_audio-1.2.0.dist-info/top_level.txt
naff_audio-1.2.0.dist-info/RECORD
