Metadata-Version: 2.1
Name: naff-audio
Version: 1.2.0
Home-page: 
Author: LordOfPolls
Author-email: lordofpolls.dev@gmail.com
Classifier: Intended Audience :: Developers
Classifier: License :: OSI Approved :: MIT License
Classifier: Natural Language :: English
Classifier: Operating System :: OS Independent
Classifier: Programming Language :: Python :: 3
Classifier: Programming Language :: Python :: 3.10
Classifier: Topic :: Software Development :: Libraries
Classifier: Topic :: Software Development :: Libraries :: Python Modules
Classifier: Topic :: Documentation
Classifier: Typing :: Typed
Requires-Python: >=3.10
License-File: LICENSE.md
Requires-Dist: naff[voice]
Requires-Dist: yt-dlp
